{
  "number": 244,
  "ayahsNumber": 9,
  "ayahs": [
    {
      "number": 1666,
      "text": "فَلَمَّا جَهَّزَهُمْ بِجَهَازِهِمْ جَعَلَ السِّقَايَةَ فِي رَحْلِ أَخِيهِ ثُمَّ أَذَّنَ مُؤَذِّنٌ أَيَّتُهَا الْعِيرُ إِنَّكُمْ لَسَارِقُونَ",
      "surah": {
        "number": 12,
        "name": "سورة يوسف",
        "englishName": "Yusuf",
        "englishNameTranslation": "Joseph",
        "revelationType": "Meccan",
        "numberOfAyahs": 111
      },
      "numberInSurah": 70,
      "juz": 13,
      "manzil": 3,
      "page": 244,
      "ruku": 201,
      "hizbQuarter": 97,
      "sajda": false,
      "tafsier": {
        "ibnkther": "فَلَمَّا جَهَّزَهُم بِجَهَازِهِمۡ جَعَلَ ٱلسِّقَايَةَ فِي رَحۡلِ أَخِيهِ ثُمَّ أَذَّنَ مُؤَذِّنٌ أَيَّتُهَا ٱلۡعِيرُ إِنَّكُمۡ لَسَٰرِقُونَ ٠٧\n                                    \n                                    \n                                    لما جهزهم وحمل لهم أبعرتهم طعاما ، أمر بعض فتيانه أن يضع \" السقاية \" ، وهي : إناء من فضة في قول الأكثرين . وقيل : من ذهب - قاله ابن زيد - كان يشرب فيه ، ويكيل للناس به من عزة الطعام إذ ذاك ، قاله ابن عباس ، ومجاهد ، وقتادة ، والضحاك ، وعبد الرحمن بن زيد .\nوقال شعبة ، عن أبي بشر ، عن سعيد بن جبير ، عن ابن عباس : ( صواع الملك ) قال : كان من فضة يشربون فيه ، وكان مثل المكوك ، وكان للعباس مثله في الجاهلية ، فوضعها في متاع بنيامين من حيث لا يشعر أحد ، ثم نادى مناد بينهم : ( أيتها العير إنكم لسارقون )\n                                    ",
        "qortoby": "فَلَمَّا جَهَّزَهُم بِجَهَازِهِمۡ جَعَلَ ٱلسِّقَايَةَ فِي رَحۡلِ أَخِيهِ ثُمَّ أَذَّنَ مُؤَذِّنٌ أَيَّتُهَا ٱلۡعِيرُ إِنَّكُمۡ لَسَٰرِقُونَ ٠٧\n                                    \n                                    \n                                    قوله تعالى : فلما جهزهم بجهازهم جعل السقاية في رحل أخيه لما عرف بنيامين أنه يوسف قال له : لا تردني إليهم ، فقال : قد علمت اغتمام يعقوب بي فيزداد غمه ، فأبى بنيامين الخروج ; فقال يوسف : لا يمكن حبسك إلا بعد أن أنسبك إلى ما لا يجمل بك : فقال : لا أبالي ! فدس الصاع في رحله ; إما بنفسه من حيث لم يطلع عليه أحد ، أو أمر بعض خواصه بذلك . والتجهيز التسريح وتنجيز الأمر ; ومنه جهز على الجريح أي قتله ، ونجز أمره . والسقاية والصواع شيء واحد ; إناء له رأسان في وسطه مقبض ، كان الملك يشرب منه من الرأس الواحد ، ويكال الطعام بالرأس الآخر ; قاله النقاش عن ابن عباس ، وكل شيء يشرب به فهو صواع ; وأنشد :\nنشرب الخمر بالصواع جهارا\nواختلف في جنسه ; فروى شعبة عن أبي بشر عن سعيد بن جبير عن ابن عباس قال : كان صواع الملك شيئا من فضة يشبه المكوك ، من فضة مرصعا بالجوهر ، يجعل على الرأس ; وكان للعباس واحد في الجاهلية ، وسأل نافع بن الأزرق ما الصواع ؟ قال : الإناء ; قال فيه الأعشى :\nله درمك في رأسه ومشارب وقدر وطباخ وصاع وديسق\nوقال عكرمة : كان من فضة . وقال عبد الرحمن بن زيد : كان من ذهب ; وبه كال طعامهم مبالغة في إكرامهم . وقيل : إنما كان يكال به لعزة الطعام . والصاع يذكر ويؤنث ; فمن أنثه قال : أصوع ; مثل أدور ، ومن ذكره قال أصواع ; مثل أثواب . وقال مجاهد وأبو صالح : الصاع الطرجهالة بلغة حمير . وفيه قراءات : \" صواع \" قراءة العامة ; و \" صوغ \" بالغين المعجمة ، وهي قراءة يحيى بن يعمر ; قال : وكان إناء أصيغ من ذهب . \" وصوع \" بالعين غير المعجمة قراءة أبي رجا . \" وصوع \" بصاد مضمومة وواو ساكنة وعين غير معجمة قراءة أبي . \" وصياع \" بياء بين الصاد والألف ; قراءة سعيد بن جبير . \" وصاع \" بألف بين الصاد والعين ; وهي قراءة أبي هريرة .\nقوله تعالى : ثم أذن مؤذن أيتها العير إنكم لسارقون أي نادى مناد وأعلم . وأذن للتكثير ; فكأنه نادى مرارا أيتها العير . والعير ما امتير عليه من الحمير والإبل والبغال . قال مجاهد : كان عيرهم حميرا . قال أبو عبيدة : العير الإبل المرحولة المركوبة ; والمعنى : يا أصحاب العير ، كقوله : واسأل القرية ويا خيل الله اركبي : أي يا أصحاب خيل الله ، وسيأتي . وهنا اعتراضان : الأول : إن قيل : كيف رضي بنيامين بالقعود طوعا وفيه عقوق الأب بزيادة الحزن ، ووافقه على ذلك يوسف ؟ وكيف نسب يوسف السرقة إلى إخوته وهم براء وهو - الثاني - فالجواب عن الأول : أن الحزن كان قد غلب على يعقوب بحيث لا يؤثر فيه فقد بنيامين كل التأثير ، أولا تراه لما فقده قال : يا أسفى على يوسف ولم يعرج على بنيامين ; ولعل يوسف إنما وافقه على القعود بوحي ; فلا اعتراض . وأما نسبة يوسف السرقة إلى إخوته فالجواب : أن القوم كانوا قد سرقوه من أبيه فألقوه في الجب ، ثم باعوه ; فاستحقوا هذا الاسم بذلك الفعل ، فصدق إطلاق ذلك عليهم . جواب آخر - وهو أنه أراد أيتها العير حالكم حال السراق ; والمعنى : إن شيئا لغيركم صار عندكم من غير رضا الملك ولا علمه . جواب آخر - وهو أن ذلك كان حيلة لاجتماع شمله بأخيه ، وفصله عنهم إليه ، وهذا بناء على أن بنيامين لم يعلم بدس الصاع في رحله ، ولا أخبره بنفسه . وقد قيل : إن معنى الكلام الاستفهام ; أي أوإنكم لسارقون ؟ كقوله : وتلك نعمة أي أوتلك نعمة تمنها علي ؟ والغرض ألا يعزى إلى يوسف - صلى الله عليه وسلم - الكذب .\n                                    ",
        "saadi": "فَلَمَّا جَهَّزَهُم بِجَهَازِهِمۡ جَعَلَ ٱلسِّقَايَةَ فِي رَحۡلِ أَخِيهِ ثُمَّ أَذَّنَ مُؤَذِّنٌ أَيَّتُهَا ٱلۡعِيرُ إِنَّكُمۡ لَسَٰرِقُونَ ٠٧\n                                        \n                                        \n                                        \n                                        { فَلَمَّا جَهَّزَهُمْ بِجَهَازِهِمْ } أي: كال لكل واحد من إخوته، ومن جملتهم أخوه هذا. { جَعَلَ السِّقَايَةَ } وهو: الإناء الذي يشرب به، ويكال فيه { فِي رَحْلِ أَخِيهِ ثُمَّ } أوعوا متاعهم، فلما انطلقوا ذاهبين، { أَذَّنَ مُؤَذِّنٌ أَيَّتُهَا الْعِيرُ إِنَّكُمْ لَسَارِقُونَ } ولعل هذا المؤذن، لم يعلم بحقيقة الحال.\n                                    "
      },
      "originalText": "فَلَمَّا جَهَّزَهُم بِجَهَازِهِمۡ جَعَلَ ٱلسِّقَايَةَ فِي رَحۡلِ أَخِيهِ ثُمَّ أَذَّنَ مُؤَذِّنٌ أَيَّتُهَا ٱلۡعِيرُ إِنَّكُمۡ لَسَٰرِقُونَ ٠٧ "
    },
    {
      "number": 1667,
      "text": "قَالُوا وَأَقْبَلُوا عَلَيْهِمْ مَاذَا تَفْقِدُونَ",
      "surah": {
        "number": 12,
        "name": "سورة يوسف",
        "englishName": "Yusuf",
        "englishNameTranslation": "Joseph",
        "revelationType": "Meccan",
        "numberOfAyahs": 111
      },
      "numberInSurah": 71,
      "juz": 13,
      "manzil": 3,
      "page": 244,
      "ruku": 201,
      "hizbQuarter": 97,
      "sajda": false,
      "tafsier": {
        "ibnkther": "قَالُواْ وَأَقۡبَلُواْ عَلَيۡهِم مَّاذَا تَفۡقِدُونَ ١٧\n                                    \n                                    \n                                    فالتفتوا إلى المنادي وقالوا : ( ماذا تفقدون)\n                                    ",
        "qortoby": "قَالُواْ وَأَقۡبَلُواْ عَلَيۡهِم مَّاذَا تَفۡقِدُونَ ١٧\n                                    \n                                    \n                                    قَالُوا وَأَقْبَلُوا عَلَيْهِم مَّاذَا تَفْقِدُونَ\n                                    ",
        "saadi": "قَالُواْ وَأَقۡبَلُواْ عَلَيۡهِم مَّاذَا تَفۡقِدُونَ ١٧\n                                        \n                                        \n                                        \n                                        { قَالُوا } أي: إخوة يوسف { وَأَقْبَلُوا عَلَيْهِمْ } لإبعاد التهمة، فإن السارق ليس له همٌّ إلا البعد والانطلاق عمن سرق منه، لتسلم له سرقته، وهؤلاء جاءوا مقبلين إليهم، ليس لهم همٌّ إلا إزالة التهمة التي رموا بها عنهم، فقالوا في هذه الحال: { مَاذَا تَفْقِدُونَ } ولم يقولوا: \"ما الذي سرقنا\" لجزمهم بأنهم براء من السرقة.\n                                    "
      },
      "originalText": "قَالُواْ وَأَقۡبَلُواْ عَلَيۡهِم مَّاذَا تَفۡقِدُونَ ١٧"
    },
    {
      "number": 1668,
      "text": "قَالُوا نَفْقِدُ صُوَاعَ الْمَلِكِ وَلِمَنْ جَاءَ بِهِ حِمْلُ بَعِيرٍ وَأَنَا بِهِ زَعِيمٌ",
      "surah": {
        "number": 12,
        "name": "سورة يوسف",
        "englishName": "Yusuf",
        "englishNameTranslation": "Joseph",
        "revelationType": "Meccan",
        "numberOfAyahs": 111
      },
      "numberInSurah": 72,
      "juz": 13,
      "manzil": 3,
      "page": 244,
      "ruku": 201,
      "hizbQuarter": 97,
      "sajda": false,
      "tafsier": {
        "ibnkther": "قَالُواْ نَفۡقِدُ صُوَاعَ ٱلۡمَلِكِ وَلِمَن جَآءَ بِهِۦ حِمۡلُ بَعِيرٖ وَأَنَا۠ بِهِۦ زَعِيمٞ ٢٧\n                                    \n                                    \n                                    ( قالوا نفقد صواع الملك ) أي : صاعه الذي يكيل به ، ( ولمن جاء به حمل بعير ) وهذا من باب الجعالة ، ( وأنا به زعيم ) وهذا من باب الضمان والكفالة .\n                                    ",
        "qortoby": "قَالُواْ نَفۡقِدُ صُوَاعَ ٱلۡمَلِكِ وَلِمَن جَآءَ بِهِۦ حِمۡلُ بَعِيرٖ وَأَنَا۠ بِهِۦ زَعِيمٞ ٢٧\n                                    \n                                    \n                                    قوله تعالى : قالوا وأقبلوا عليهم ماذا تفقدون قالوا نفقد صواع الملك ولمن جاء به حمل بعير وأنا به زعيم\nفيه سبع مسائل :\nالأولى : قوله تعالى : ولمن جاء به حمل بعير وأنا به زعيم . البعير هنا الجمل في قول أكثر المفسرين . وقيل : إنه الحمار ، وهي لغة لبعض العرب ; قاله مجاهد واختاره . وقال مجاهد : الزعيم هو المؤذن الذي قال : أيتها العير . والزعيم والكفيل والحميل والضمين والقبيل سواء والزعيم الرئيس . قال :\nوإني زعيم إن رجعت مملكا بسير ترى منه الفرانق أزورا\nوقالت ليلى الأخيلية ترثي أخاها :\nومخرق عنه القميص تخاله يوم اللقاء من الحياء سقيما\nحتى إذا رفع اللواء رأيته تحت اللواء على الخميس زعيما\nالثانية : إن قيل : كيف ضمن حمل البعير وهو مجهول ، وضمان المجهول لا يصح ؟ قيل له : حمل البعير كان معينا معلوما عندهم كالوسق ; فصح ضمانه ، غير أنه كان بدل مال للسارق ، ولا يحل للسارق ذلك ، فلعله كان يصح في شرعهم أو كان هذا جعالة ، وبذل مال لمن كان يفتش ويطلب .\nالثالثة : قال بعض العلماء : في هذه الآية دليلان : أحدهما : جواز الجعل وقد أجيز للضرورة ; فإنه يجوز فيه من الجهالة ما لا يجوز . في غيره ; فإذا قال الرجل : من فعل كذا فله كذا صح . وشأن الجعل أن يكون أحد الطرفين معلوما والآخر مجهولا للضرورة إليه ; بخلاف الإجارة ; فإنه يتقدر فيها العوض والمعوض من الجهتين ; وهو من العقود الجائزة التي يجوز لأحدهما فسخه ; إلا أن المجعول له يجوز أن يفسخه قبل الشروع وبعده ، إذا رضي بإسقاط حقه ، وليس للجاعل أن يفسخه إذا شرع المجعول له في العمل . ولا يشترط في عقد الجعل حضور المتعاقدين ، كسائر العقود ; لقوله : ولمن جاء به حمل بعير وبهذا كله قال الشافعي .\nالرابعة : متى قال الإنسان ، من جاء بعبدي الآبق فله دينار لزمه ما جعله فيه إذا جاء به ; فلو جاء به من غير ضمان لزمه إذا جاء به على طلب الأجرة ; وذلك أن النبي - صلى الله عليه وسلم - قال : من جاء بآبق فله أربعون درهما ولم يفصل بين من جاء به من عقد ضمان أو غير عقد . قال ابن خوير منداد ولهذا قال أصحابنا : إن من فعل بالإنسان ما يجب عليه أن يفعله بنفسه من مصالحه لزمه ذلك ، وكان له أجر مثله إن كان ممن يفعل ذلك بالأجر .\nقلت : وخالفنا في هذا كله الشافعي .\nالخامسة : الدليل الثاني : جواز الكفالة على الرجل ; لأن المؤذن الضامن هو غير يوسف - عليه السلام - قال علماؤنا : إذا قال الرجل تحملت أو تكفلت أو ضمنت أو وأنا حميل لك أو زعيم أو كفيل أو ضامن أو قبيل ، أو هو لك عندي أو علي أو إلي أو قبلي فذلك كله حمالة لازمة ، وقد اختلف الفقهاء فيمن تكفل بالنفس أو بالوجه ، هل يلزمه ضمان المال أم لا ؟ فقال الكوفيون : من تكفل بنفس رجل لم يلزمه الحق الذي على المطلوب إن مات ; وهو أحد قولي الشافعي في المشهور عنه . وقال مالك والليث والأوزاعي : إذا تكفل بنفسه وعليه مال فإنه إن لم يأت به غرم المال ، ويرجع به إلى المطلوب ; فإن اشترط ضمان نفسه أو وجهه وقال : لا أضمن المال فلا شيء عليه من المال ; والحجة لمن أوجب غرم المال أن الكفيل قد علم أن المضمون وجهه لا يطلب بدم ، وإنما يطلب بمال ; فإذا ضمنه له ولم يأته به فكأنه فوته عليه ، وعزه منه ; فلذلك لزمه المال . واحتج الطحاوي للكوفيين فقال : أما ضمان المال بموت المكفول به فلا معنى له ; لأنه إنما تكفل بالنفس ولم يتكفل بالمال ، فمحال أن يلزمه ما لم يتكفل به .\nالسادسة : واختلف العلماء إذا تكفل رجل عن رجل بمال ; هل للطالب أن يأخذ من شاء منهما ؟ فقال الثوري والكوفيون والأوزاعي والشافعي وأحمد وإسحاق : يأخذ من شاء حتى يستوفي حقه ; وهذا كان قول مالك ثم رجع عنه فقال : لا يؤخذ الكفيل إلا أن يفلس الغريم أو يغيب ; لأن التبدية بالذي عليه الحق أولى ، إلا أن يكون معدما فإنه يؤخذ من الحميل ، لأنه معذور في أخذه في هذه الحالة ; وهذا قول حسن . والقياس أن للرجل مطالبة أي الرجلين شاء . وقال ابن أبي ليلى : إذا ضمن الرجل عن صاحبه مالا تحول على الكفيل وبرئ صاحب الأصل ، إلا أن يشترط المكفول له عليهما أن يأخذ أيهما شاء ; واحتج ببراءة الميت من الدين ، بضمان أبي قتادة ، وبنحوه قال أبو ثور .\nالسابعة : الزعامة لا تكون إلا في الحقوق التي تجوز النيابة فيها ، مما يتعلق بالذمة من الأموال ، وكان ثابتا مستقرا ; فلا تصح الحمالة بالكتابة لأنها ليست بدين ثابت مستقر ; لأن العبد إن عجز رق وانفسخت الكتابة ; وأما كل حق لا يقوم به أحد عن أحد كالحدود فلا كفالة فيه ، ويسجن المدعى عليه الحد ، حتى ينظر في أمره . وشذ أبو يوسف ومحمد فأجازا الكفالة في الحدود والقصاص ، وقالا : إذا قال المقذوف أو المدعي القصاص بينتي حاضرة كفله ثلاثة أيام ; واحتج لهم الطحاوي بما رواه حمزة بن عمرو عن عمر وابن مسعود وجرير بن عبد الله والأشعث أنهم حكموا بالكفالة بالنفس بمحضر الصحابة .\n\n                                    ",
        "saadi": "قَالُواْ نَفۡقِدُ صُوَاعَ ٱلۡمَلِكِ وَلِمَن جَآءَ بِهِۦ حِمۡلُ بَعِيرٖ وَأَنَا۠ بِهِۦ زَعِيمٞ ٢٧\n                                        \n                                        \n                                        \n                                        { قَالُوا نَفْقِدُ صُوَاعَ الْمَلِكِ وَلِمَنْ جَاءَ بِهِ حِمْلُ بَعِيرٍ } أي: أجرة له على وجدانه { وَأَنَا بِهِ زَعِيمٌ } أي: كفيل، وهذا يقوله المؤذن المتفقد.\n                                    "
      },
      "originalText": "قَالُواْ نَفۡقِدُ صُوَاعَ ٱلۡمَلِكِ وَلِمَن جَآءَ بِهِۦ حِمۡلُ بَعِيرٖ وَأَنَا۠ بِهِۦ زَعِيمٞ ٢٧"
    },
    {
      "number": 1669,
      "text": "قَالُوا تَاللَّهِ لَقَدْ عَلِمْتُمْ مَا جِئْنَا لِنُفْسِدَ فِي الْأَرْضِ وَمَا كُنَّا سَارِقِينَ",
      "surah": {
        "number": 12,
        "name": "سورة يوسف",
        "englishName": "Yusuf",
        "englishNameTranslation": "Joseph",
        "revelationType": "Meccan",
        "numberOfAyahs": 111
      },
      "numberInSurah": 73,
      "juz": 13,
      "manzil": 3,
      "page": 244,
      "ruku": 201,
      "hizbQuarter": 97,
      "sajda": false,
      "tafsier": {
        "ibnkther": "قَالُواْ تَٱللَّهِ لَقَدۡ عَلِمۡتُم مَّا جِئۡنَا لِنُفۡسِدَ فِي ٱلۡأَرۡضِ وَمَا كُنَّا سَٰرِقِينَ ٣٧\n                                    \n                                    \n                                    لما اتهمهم أولئك الفتيان بالسرقة ، قال لهم إخوة يوسف : ( تالله لقد علمتم ما جئنا لنفسد في الأرض وما كنا سارقين ) أي : لقد تحققتم وعلمتم منذ عرفتمونا - لأنهم شاهدوا منهم سيرة حسنة - أنا ما جئنا للفساد في الأرض ، وما كنا سارقين ، أي : ليست سجايانا تقتضي هذه الصفة ،\n                                    ",
        "qortoby": "قَالُواْ تَٱللَّهِ لَقَدۡ عَلِمۡتُم مَّا جِئۡنَا لِنُفۡسِدَ فِي ٱلۡأَرۡضِ وَمَا كُنَّا سَٰرِقِينَ ٣٧\n                                    \n                                    \n                                    قوله تعالى : قالوا تالله لقد علمتم ما جئنا لنفسد في الأرض وما كنا سارقين\nقوله تعالى : قالوا تالله لقد علمتم ما جئنا لنفسد في الأرض يروى أنهم كانوا لا ينزلون على أحد ظلما ، ولا يرعون زرع أحد ، وأنهم جمعوا على أفواه إبلهم الأكمة لئلا تعيث في زروع الناس .\nوما كنا سارقين يروى أنهم ردوا البضاعة التي كانت في رحالهم ; أي فمن رد ما وجد فكيف يكون سارقا ؟ ! .\n                                    ",
        "saadi": "قَالُواْ تَٱللَّهِ لَقَدۡ عَلِمۡتُم مَّا جِئۡنَا لِنُفۡسِدَ فِي ٱلۡأَرۡضِ وَمَا كُنَّا سَٰرِقِينَ ٣٧\n                                        \n                                        \n                                        \n                                        { قَالُوا تَاللَّهِ لَقَدْ عَلِمْتُمْ مَا جِئْنَا لِنُفْسِدَ فِي الْأَرْضِ } بجميع أنواع المعاصي، { وَمَا كُنَّا سَارِقِينَ } فإن السرقة من أكبر أنواع الفساد في الأرض، وإنما أقسموا على علمهم أنهم ليسوا مفسدين ولا سارقين، لأنهم عرفوا أنهم سبروا من أحوالهم ما يدلهم على عفتهم وورعهم، وأن هذا الأمر لا يقع منهم بعلم من اتهموهم، وهذا أبلغ في نفي التهمة، من أن لو قالوا: { تالله لم نفسد في الأرض ولم نسرق }.\n                                    "
      },
      "originalText": "قَالُواْ تَٱللَّهِ لَقَدۡ عَلِمۡتُم مَّا جِئۡنَا لِنُفۡسِدَ فِي ٱلۡأَرۡضِ وَمَا كُنَّا سَٰرِقِينَ ٣٧"
    },
    {
      "number": 1670,
      "text": "قَالُوا فَمَا جَزَاؤُهُ إِنْ كُنْتُمْ كَاذِبِينَ",
      "surah": {
        "number": 12,
        "name": "سورة يوسف",
        "englishName": "Yusuf",
        "englishNameTranslation": "Joseph",
        "revelationType": "Meccan",
        "numberOfAyahs": 111
      },
      "numberInSurah": 74,
      "juz": 13,
      "manzil": 3,
      "page": 244,
      "ruku": 201,
      "hizbQuarter": 97,
      "sajda": false,
      "tafsier": {
        "ibnkther": "قَالُواْ فَمَا جَزَٰٓؤُهُۥٓ إِن كُنتُمۡ كَٰذِبِينَ ٤٧\n                                    \n                                    \n                                    فقال لهم الفتيان : ( فما جزاؤه ) أي : السارق ، إن كان فيكم ) إن كنتم كاذبين ) أي : أي شيء يكون عقوبته إن وجدنا فيكم من أخذه ؟\n                                    ",
        "qortoby": "قَالُواْ فَمَا جَزَٰٓؤُهُۥٓ إِن كُنتُمۡ كَٰذِبِينَ ٤٧\n                                    \n                                    \n                                    قوله تعالى : قالوا فما جزاؤه إن كنتم كاذبين المعنى : فما جزاء الفاعل إن بان كذبكم ؟\n                                    ",
        "saadi": "قَالُواْ فَمَا جَزَٰٓؤُهُۥٓ إِن كُنتُمۡ كَٰذِبِينَ ٤٧\n                                        \n                                        \n                                        \n                                        { قَالُوا فَمَا جَزَاؤُهُ } أي: جزاء هذا الفعل { إِنْ كُنْتُمْ كَاذِبِينَ } بأن كان معكم؟\n                                    "
      },
      "originalText": "قَالُواْ فَمَا جَزَٰٓؤُهُۥٓ إِن كُنتُمۡ كَٰذِبِينَ ٤٧"
    },
    {
      "number": 1671,
      "text": "قَالُوا جَزَاؤُهُ مَنْ وُجِدَ فِي رَحْلِهِ فَهُوَ جَزَاؤُهُ ۚ كَذَٰلِكَ نَجْزِي الظَّالِمِينَ",
      "surah": {
        "number": 12,
        "name": "سورة يوسف",
        "englishName": "Yusuf",
        "englishNameTranslation": "Joseph",
        "revelationType": "Meccan",
        "numberOfAyahs": 111
      },
      "numberInSurah": 75,
      "juz": 13,
      "manzil": 3,
      "page": 244,
      "ruku": 201,
      "hizbQuarter": 97,
      "sajda": false,
      "tafsier": {
        "ibnkther": "قَالُواْ جَزَٰٓؤُهُۥ مَن وُجِدَ فِي رَحۡلِهِۦ فَهُوَ جَزَٰٓؤُهُۥۚ كَذَٰلِكَ نَجۡزِي ٱلظَّٰلِمِينَ ٥٧\n                                    \n                                    \n                                    ( قالوا جزاؤه من وجد في رحله فهو جزاؤه كذلك نجزي الظالمين )\nوهكذا كانت شريعة إبراهيم : أن السارق يدفع إلى المسروق منه . وهذا هو الذي أراد يوسف ، عليه السلام\n                                    ",
        "qortoby": "قَالُواْ جَزَٰٓؤُهُۥ مَن وُجِدَ فِي رَحۡلِهِۦ فَهُوَ جَزَٰٓؤُهُۥۚ كَذَٰلِكَ نَجۡزِي ٱلظَّٰلِمِينَ ٥٧\n                                    \n                                    \n                                    فأجاب إخوة يوسف : جزاؤه من وجد في رحله فهو جزاؤه أي يستعبد ويسترق . فجزاؤه مبتدأ ، و من وجد في رحله خبره ; والتقدير : جزاؤه استعباد من وجد في رحله ; فهو كناية عن الاستعباد ; وفي الجملة معنى التوكيد ، كما تقول : جزاء من سرق القطع فهذا جزاؤه .\nكذلك نجزي الظالمين أي كذلك نفعل في الظالمين إذا سرقوا أن يسترقوا ، وكان هذا من دين يعقوب - عليه السلام - وحكمه . وقولهم هذا قول من لم يسترب نفسه ; لأنهم التزموا استرقاق من وجد في رحله ، وكان حكم السارق عند أهل مصر أن يغرم ضعفي ما أخذ ; قاله الحسن والسدي وغيرهما . مسألة : قد تقدم في سورة \" المائدة \" أن القطع في السرقة ناسخ لما تقدم من الشرائع ، أو لما كان في شرع يعقوب من استرقاق السارق ، والله أعلم .\n                                    ",
        "saadi": "قَالُواْ جَزَٰٓؤُهُۥ مَن وُجِدَ فِي رَحۡلِهِۦ فَهُوَ جَزَٰٓؤُهُۥۚ كَذَٰلِكَ نَجۡزِي ٱلظَّٰلِمِينَ ٥٧\n                                        \n                                        \n                                        \n                                        { قَالُوا جَزَاؤُهُ مَنْ وُجِدَ فِي رَحْلِهِ فَهُوَ } أي: الموجود في رحله { جَزَاؤُهُ } بأن يتملكه صاحب السرقة، وكان هذا في دينهم أن السارق إذا ثبتت عليه السرقة كان ملكا لصاحب المال المسروق، ولهذا قالوا: { كَذَلِكَ نَجْزِي الظَّالِمِينَ }\n                                    "
      },
      "originalText": "قَالُواْ جَزَٰٓؤُهُۥ مَن وُجِدَ فِي رَحۡلِهِۦ فَهُوَ جَزَٰٓؤُهُۥۚ كَذَٰلِكَ نَجۡزِي ٱلظَّٰلِمِينَ ٥٧"
    },
    {
      "number": 1672,
      "text": "فَبَدَأَ بِأَوْعِيَتِهِمْ قَبْلَ وِعَاءِ أَخِيهِ ثُمَّ اسْتَخْرَجَهَا مِنْ وِعَاءِ أَخِيهِ ۚ كَذَٰلِكَ كِدْنَا لِيُوسُفَ ۖ مَا كَانَ لِيَأْخُذَ أَخَاهُ فِي دِينِ الْمَلِكِ إِلَّا أَنْ يَشَاءَ اللَّهُ ۚ نَرْفَعُ دَرَجَاتٍ مَنْ نَشَاءُ ۗ وَفَوْقَ كُلِّ ذِي عِلْمٍ عَلِيمٌ",
      "surah": {
        "number": 12,
        "name": "سورة يوسف",
        "englishName": "Yusuf",
        "englishNameTranslation": "Joseph",
        "revelationType": "Meccan",
        "numberOfAyahs": 111
      },
      "numberInSurah": 76,
      "juz": 13,
      "manzil": 3,
      "page": 244,
      "ruku": 201,
      "hizbQuarter": 97,
      "sajda": false,
      "tafsier": {
        "ibnkther": "فَبَدَأَ بِأَوۡعِيَتِهِمۡ قَبۡلَ وِعَآءِ أَخِيهِ ثُمَّ ٱسۡتَخۡرَجَهَا مِن وِعَآءِ أَخِيهِۚ كَذَٰلِكَ كِدۡنَا لِيُوسُفَۖ مَا كَانَ لِيَأۡخُذَ أَخَاهُ فِي دِينِ ٱلۡمَلِكِ إِلَّآ أَن يَشَآءَ ٱللَّهُۚ نَرۡفَعُ دَرَجَٰتٖ مَّن نَّشَآءُۗ وَفَوۡقَ كُلِّ ذِي عِلۡمٍ عَلِيمٞ ٦٧\n                                    \n                                    \n                                    ولهذا بدأ بأوعيتهم قبل وعاء أخيه ، أي فتشها قبله ، تورية ، ( ثم استخرجها من وعاء أخيه ) فأخذه منهم بحكم اعترافهم والتزامهم وإلزاما لهم بما يعتقدونه; ولهذا قال تعالى : ( كذلك كدنا ليوسف ) وهذا من الكيد المحبوب المراد الذي يحبه الله ويرضاه ، لما فيه من الحكمة والمصلحة المطلوبة .\nوقوله : ( ما كان ليأخذ أخاه في دين الملك ) أي : لم يكن له أخذه في حكم ملك مصر ، قاله الضحاك وغيره .\nوإنما قيض الله له أن التزم له إخوته بما التزموه ، وهو كان يعلم ذلك من شريعتهم; ولهذا مدحه تعالى فقال : ( نرفع درجات من نشاء ) كما قال تعالى : ( يرفع الله الذين آمنوا منكم والذين أوتوا العلم درجات والله بما تعملون خبير ) [ المجادلة : 11 ] .\n( وفوق كل ذي علم عليم ) قال الحسن البصري : ليس عالم إلا فوقه عالم ، حتى ينتهي إلى الله عز وجل . وكذا روى عبد الرزاق ، عن سفيان الثوري ، عن عبد الأعلى الثعلبي ، عن سعيد بن جبير قال : كنا عند ابن عباس فتحدث بحديث عجيب ، فتعجب رجل فقال : الحمد لله فوق كل ذي علم عليم [ فقال ابن عباس : بئس ما قلت ، الله العليم ، وهو فوق كل عالم ] وكذا روى سماك ، عن عكرمة ، عن ابن عباس : ( وفوق كل ذي علم عليم ) قال : يكون هذا أعلم من هذا ، وهذا أعلم من هذا ، والله فوق كل عالم . وهكذا قال عكرمة .\nوقال قتادة : ( وفوق كل ذي علم عليم ) حتى ينتهي العلم إلى الله ، منه بدئ وتعلمت العلماء ، وإليه يعود ، وفي قراءة عبد الله \" وفوق كل عالم عليم \" .\n                                    ",
        "qortoby": "فَبَدَأَ بِأَوۡعِيَتِهِمۡ قَبۡلَ وِعَآءِ أَخِيهِ ثُمَّ ٱسۡتَخۡرَجَهَا مِن وِعَآءِ أَخِيهِۚ كَذَٰلِكَ كِدۡنَا لِيُوسُفَۖ مَا كَانَ لِيَأۡخُذَ أَخَاهُ فِي دِينِ ٱلۡمَلِكِ إِلَّآ أَن يَشَآءَ ٱللَّهُۚ نَرۡفَعُ دَرَجَٰتٖ مَّن نَّشَآءُۗ وَفَوۡقَ كُلِّ ذِي عِلۡمٍ عَلِيمٞ ٦٧\n                                    \n                                    \n                                    قوله : فبدأ بأوعيتهم قبل وعاء أخيه ثم استخرجها من وعاء أخيه كذلك كدنا ليوسف ما كان ليأخذ أخاه في دين الملك إلا أن يشاء الله نرفع درجات من نشاء وفوق كل ذي علم عليم\nقوله تعالى : فبدأ بأوعيتهم قبل وعاء أخيه إنما بدأ يوسف برحالهم لنفي التهمة والريبة من قلوبهم إن بدأ بوعاء أخيه . والوعاء يقال بضم الواو وكسرها ، لغتان ; وهو ما يحفظ فيه المتاع ويصونه .\nثم استخرجها من وعاء أخيه يعني بنيامين ; أي استخرج السقاية أو الصواع عند من يؤنث ، وقال : ولمن جاء به فذكر ; فلما رأى ذلك إخوته نكسوا رءوسهم ، وظنوا الظنون كلها ، وأقبلوا عليه وقالوا ويلك يا بنيامين ! ما رأينا كاليوم قط ، ولدت أمك \" راحيل \" أخوين لصين ! قال لهم أخوهم : والله ما سرقته ، ولا علم لي بمن وضعه في متاعي . ويروى أنهم قالوا له : يا بنيامين ! أسرقت ؟ قال : لا والله ; قالوا : فمن جعل الصواع في رحلك ؟ قال : الذي جعل البضاعة في رحالكم . ويقال : إن المفتش كان إذا فرغ من رحل رجل استغفر الله - عز وجل - تائبا من فعله ذلك ; وظاهر كلام قتادة وغيره أن المستغفر كان يوسف ; لأنه كان يفتشهم ويعلم أين الصواع حتى فرغ منهم ، وانتهى إلى رحل بنيامين فقال : ما أظن هذا الفتى رضي بهذا ولا أخذ شيئا ، فقال له إخوته : والله لا نبرح حتى تفتشه ; فهو أطيب لنفسك ونفوسنا ; ففتش فأخرج السقاية ; وهذا التفتيش من يوسف يقتضي أن المؤذن سرقهم برأيه ; فيقال : إن جميع ذلك كان أمر من الله تعالى ; ويقوي ذلك قوله تعالى : كذلك كدنا ليوسف .\nقوله تعالى : كذلك كدنا ليوسف فيه ثلاث مسائل :\nالأولى : قوله تعالى : \" كدنا \" معناه صنعنا ; عن ابن عباس . والقتبي : دبرنا . ابن الأنباري : أردنا ; قال الشاعر :\nكادت وكدت وتلك خير إرادة لو عاد من عهد الصبا ما قد مضى\nوفيه جواز التوصل إلى الأغراض بالحيل إذا لم تخالف شريعة ، ولا هدمت أصلا ، خلافا لأبي حنيفة في تجويزه الحيل وإن خالفت الأصول ، وخرمت التحليل .\nالثانية : أجمع العلماء على أن للرجل قبل حلول الحول التصرف في ماله بالبيع والهبة إذا لم ينو الفرار من الصدقة ; وأجمعوا على أنه إذا حال الحول وأظل الساعي أنه لا يحل له التحيل ولا النقصان ، ولا أن يفرق بين مجتمع ، ولا أن يجمع بين متفرق . وقال مالك : إذا فوت من ماله شيئا ينوي به الفرار من الزكاة قبل الحول بشهر أو نحوه لزمته الزكاة عند الحول ، أخذا منه بقوله - عليه السلام - : \" خشية الصدقة \" . وقال أبو حنيفة : إن نوى بتفريقه الفرار من الزكاة قبل الحول بيوم لا يضره ; لأن الزكاة لا تلزم إلا بتمام الحول ، ولا يتوجه إليه معنى قوله : خشية الصدقة إلا حينئذ . قال ابن العربي : سمعت أبا بكر محمد بن الوليد الفهري وغيره يقول : كان شيخنا قاضي القضاة أبو عبد الله محمد بن علي الدامغاني صاحب عشرات آلاف دينار من المال ، فكان إذا جاء رأس الحول دعا بنيه فقال لهم : كبرت سني ، وضعفت قوتي ، وهذا مال لا أحتاجه فهو لكم ، ثم يخرجه فيحمله الرجال على أعناقهم إلى دور بنيه ; فإذا جاء رأس الحول ودعا بنيه لأمر قالوا : يا أبانا ! إنما أملنا حياتك ، وأما المال فأي رغبة لنا فيه ما دمت حيا ; أنت ومالك لنا ، فخذه إليك ، ويسير الرجال به حتى يضعوه بين يديه ، فيرده إلى موضعه ; يريد بتبديل الملك إسقاط الزكاة على رأي أبي حنيفة في التفريق بين المجتمع ، والجمع بين المتفرق ; وهذا خطب عظيم وقد صنف البخاري - رضي الله عنه - في جامعه كتابا مقصودا فقال : \" كتاب الحيل \" .\nقلت : وترجم فيه أبوابا منها : \" باب الزكاة وألا يفرق بين مجتمع ولا يجمع بين متفرق خشية الصدقة \" . وأدخل فيه حديث أنس بن مالك ، وأن أبا بكر كتب له فريضة الصدقة ; وحديث طلحة بن عبيد الله أن أعرابيا جاء إلى رسول الله - صلى الله عليه وسلم - ثائر الرأس . الحديث ; وفي آخره : أفلح إن صدق أو دخل الجنة إن صدق . وقال بعض الناس : في عشرين ومائة بعير حقتان ; فإن أهلكها متعمدا أو وهبها أو احتال فيها فرارا من الزكاة فلا شيء عليه ; ثم أردف بحديث أبي هريرة قال : قال رسول الله - صلى الله عليه وسلم - : يكون كنز أحدكم يوم القيامة شجاعا أقرع له زبيبتان ويقول أنا كنزك الحديث ، قال المهلب : إنما قصد البخاري في هذا الباب أن يعرفك أن كل حيلة يتحيل بها أحد في إسقاط الزكاة فإن إثم ذلك عليه ; لأن النبي - صلى الله عليه وسلم - لما منع من جمع الغنم وتفريقها خشية الصدقة فهم منه هذا المعنى ، وفهم من قوله : أفلح إن صدق أن من رام أن ينقض شيئا من فرائض الله بحيلة يحتالها أنه لا يفلح ، ولا يقوم بذلك عذره عند الله ; وما أجازه الفقهاء من تصرف صاحب المال في ماله قرب حلول الحول إنما هو ما لم يرد بذلك الهرب من الزكاة ; ومن نوى ذلك فالإثم عنه غير ساقط ، والله حسيبه ; وهو كمن فر من صيام رمضان قبل رؤية الهلال بيوم ، واستعمل سفرا لا يحتاج إليه رغبة عن فرض الله الذي كتبه الله على المؤمنين ; فالوعيد متوجه عليه ; ألا ترى عقوبة من منع الزكاة يوم القيامة بأي وجه متعمدا كيف تطؤه الإبل ، ويمثل له ماله شجاعا أقرع ؟ ! وهذا يدل على أن الفرار من الزكاة لا يحل ، وهو مطالب بذلك في الآخرة .\nالثالثة : قال ابن العربي : قال بعض علماء الشافعية في قوله تعالى : كذلك كدنا ليوسف ما كان ليأخذ أخاه . دليل على وجه الحيلة إلى المباح ، واستخراج الحقوق ; وهذا وهم عظيم ; وقوله تعالى : كذلك كدنا ليوسف في الأرض قيل فيه : كما مكنا ليوسف ملك نفسه عن امرأة العزيز مكنا له ملك الأرض عن العزيز ، أو مثله مما لا يشبه ما ذكره . قال الشفعوي : ومثله قوله - عز وجل - : وخذ بيدك ضغثا فاضرب به ولا تحنث وهذا ليس حيلة ، إنما هو حمل لليمين على الألفاظ أو على المقاصد . قال الشفعوي : ومثله حديث أبي سعيد الخدري في عامل خيبر أنه أتى النبي - صلى الله عليه وسلم - بتمر جنيب الحديث ; ومقصود الشافعية من هذا الحديث أنه - عليه السلام - أمره أن يبيع جمعا ويبتاع جنيبا من الذي باع منه الجمع أو من غيره . وقالت المالكية : معناه من غيره ; لئلا يكون جنيبا بجمع ، والدراهم ربا ; كما قال ابن عباس : جريرة بجريرة والدراهم ربا .\nقوله تعالى : في دين الملك أي سلطانه ، عن ابن عباس . ابن عيسى : عاداته ، أي يظلم بلا حجة . مجاهد : في حكمه ; وهو استرقاق السراق .\nإلا أن يشاء الله أي إلا بأن يشاء الله أن يجعل السقاية في رحله تعلة وعذرا له . وقال قتادة : بل كان حكم الملك الضرب والغرم ضعفين ، ولكن شاء الله أن يجري على ألسنتهم حكم بني إسرائيل ، على ما تقدم .\nقوله تعالى : نرفع درجات من نشاء أي بالعلم والإيمان . وقرئ \" نرفع درجات من نشاء \" بمعنى : نرفع من نشاء درجات ; وقد مضى في \" الأنعام \"\nقوله : وفوق كل ذي علم عليم روى إسرائيل عن سماك عن عكرمة عن ابن عباس قال : يكون ذا أعلم من ذا وذا أعلم من ذا ، والله فوق كل عالم . وروى سفيان عن عبد الأعلى عن سعيد بن جبير قال : كنا عند ابن عباس - رحمه الله - فتحدث بحديث فتعجب منه رجل فقال : سبحان الله ! وفوق كل ذي علم عليم ; فقال ابن عباس : بئس ما قلت ; الله العليم وهو فوق كل عالم .\n                                    ",
        "saadi": "فَبَدَأَ بِأَوۡعِيَتِهِمۡ قَبۡلَ وِعَآءِ أَخِيهِ ثُمَّ ٱسۡتَخۡرَجَهَا مِن وِعَآءِ أَخِيهِۚ كَذَٰلِكَ كِدۡنَا لِيُوسُفَۖ مَا كَانَ لِيَأۡخُذَ أَخَاهُ فِي دِينِ ٱلۡمَلِكِ إِلَّآ أَن يَشَآءَ ٱللَّهُۚ نَرۡفَعُ دَرَجَٰتٖ مَّن نَّشَآءُۗ وَفَوۡقَ كُلِّ ذِي عِلۡمٍ عَلِيمٞ ٦٧\n                                        \n                                        \n                                        \n                                        { فَبَدَأَ } المفتش { بِأَوْعِيَتِهِمْ قَبْلَ وِعَاءِ أَخِيهِ } وذلك لتزول الريبة التي يظن أنها فعلت بالقصد، فلما لم يجد في أوعيتهم شيئا { اسْتَخْرَجَهَا مِنْ وِعَاءِ أَخِيهِ } ولم يقل \"وجدها، أو سرقها أخوه\" مراعاة للحقيقة الواقعة.\nفحينئذ تم ليوسف ما أراد من بقاء أخيه عنده، على وجه لا يشعر به إخوته، قال تعالى: { كَذَلِكَ كِدْنَا لِيُوسُفَ } أي: يسرنا له هذا الكيد، الذي توصل به إلى أمر غير مذموم { مَا كَانَ لِيَأْخُذَ أَخَاهُ فِي دِينِ الْمَلِكِ } لأنه ليس من دينه أن يتملك السارق، وإنما له عندهم، جزاء آخر، فلو ردت الحكومة إلى دين الملك، لم يتمكن يوسف من إبقاء أخيه عنده، ولكنه جعل الحكم منهم، ليتم له ما أراد.\nقال تعالى: { نَرْفَعُ دَرَجَاتٍ مَنْ نَشَاءُ } بالعلم النافع، ومعرفة الطرق الموصلة إلى مقصدها، كما رفعنا درجات يوسف، { وَفَوْقَ كُلِّ ذِي عِلْمٍ عَلِيمٌ } فكل عالم، فوقه من هو أعلم منه حتى ينتهي العلم إلى عالم الغيب والشهادة.\n                                    "
      },
      "originalText": "فَبَدَأَ بِأَوۡعِيَتِهِمۡ قَبۡلَ وِعَآءِ أَخِيهِ ثُمَّ ٱسۡتَخۡرَجَهَا مِن وِعَآءِ أَخِيهِۚ كَذَٰلِكَ كِدۡنَا لِيُوسُفَۖ مَا كَانَ لِيَأۡخُذَ أَخَاهُ فِي دِينِ ٱلۡمَلِكِ إِلَّآ أَن يَشَآءَ ٱللَّهُۚ نَرۡفَعُ دَرَجَٰتٖ مَّن نَّشَآءُۗ وَفَوۡقَ كُلِّ ذِي عِلۡمٍ عَلِيمٞ ٦٧"
    },
    {
      "number": 1673,
      "text": "۞ قَالُوا إِنْ يَسْرِقْ فَقَدْ سَرَقَ أَخٌ لَهُ مِنْ قَبْلُ ۚ فَأَسَرَّهَا يُوسُفُ فِي نَفْسِهِ وَلَمْ يُبْدِهَا لَهُمْ ۚ قَالَ أَنْتُمْ شَرٌّ مَكَانًا ۖ وَاللَّهُ أَعْلَمُ بِمَا تَصِفُونَ",
      "surah": {
        "number": 12,
        "name": "سورة يوسف",
        "englishName": "Yusuf",
        "englishNameTranslation": "Joseph",
        "revelationType": "Meccan",
        "numberOfAyahs": 111
      },
      "numberInSurah": 77,
      "juz": 13,
      "manzil": 3,
      "page": 244,
      "ruku": 201,
      "hizbQuarter": 98,
      "sajda": false,
      "tafsier": {
        "ibnkther": "۞ قَالُوٓاْ إِن يَسۡرِقۡ فَقَدۡ سَرَقَ أَخٞ لَّهُۥ مِن قَبۡلُۚ فَأَسَرَّهَا يُوسُفُ فِي نَفۡسِهِۦ وَلَمۡ يُبۡدِهَا لَهُمۡۚ قَالَ أَنتُمۡ شَرّٞ مَّكَانٗاۖ وَٱللَّهُ أَعۡلَمُ بِمَا تَصِفُونَ ٧٧\n                                    \n                                    \n                                    وقال إخوة يوسف لما رأوا الصواع قد أخرج من متاع بنيامين : ( إن يسرق فقد سرق أخ له من قبل ) يتنصلون إلى العزيز من التشبه به ، ويذكرون أن هذا فعل كما فعل أخ له من قبل ، يعنون به يوسف ، عليه السلام .\nقال سعيد بن جبير ، عن قتادة كان يوسف قد سرق صنما لجده ، أبي أمه ، فكسره .\nوقال محمد بن إسحاق ، عن عبد الله بن أبي نجيح ، عن مجاهد قال : كان أول ما دخل على يوسف من البلاء ، فيما بلغني ، أن عمته ابنة إسحاق ، وكانت أكبر ولد إسحاق ، وكانت إليها منطقة إسحاق ، وكانوا يتوارثونها بالكبر ، فكان من اختباها ممن وليها كان له سلما لا ينازع فيه ، يصنع فيه ما يشاء وكانيعقوب حين ولد له يوسف قد حضنته عمته ، فكان منها وإليها ، فلم يحب أحد شيئا من الأشياء حبها إياه ، حتى إذا ترعرع وبلغ سنوات وقعت نفس يعقوب عليه فأتاها ، فقال : يا أخية سلمى إلي يوسف ، فوالله ما أقدر على أن يغيب عني ساعة . قالت : فوالله ما أنا بتاركته . ثم قالت : فدعه عندي أياما أنظر إليه وأسكن عنه ، لعل ذلك يسليني عنه ، أو كما قالت . فلما خرج من عندها يعقوب ، عمدت إلى منطقة إسحاق ، فحزمتها على يوسف من تحت ثيابه ، ثم قالت : فقدت منطقة إسحاق ، عليه السلام ، فانظروا من أخذها ومن أصابها ؟ فالتمست ثم قالت : اكشفوا أهل البيت . فكشفوهم فوجدوها مع يوسف . فقالت : والله إنه لي لسلم ، أصنع فيه ما شئت . فأتاها يعقوب فأخبرته الخبر . فقال لها : أنت وذاك ، إن كان فعل ذلك فهو سلم لك ما أستطيع غير ذلك . فأمسكته فما قدر عليه يعقوب حتى ماتت . قال : فهو الذي يقول إخوة يوسف حين صنع بأخيه ما صنع حين أخذه : ( إن يسرق فقد سرق أخ له من قبل ) .\nوقوله : ( فأسرها يوسف في نفسه ) يعني : الكلمة التي بعدها ، وهي قوله : ( أنتم شر مكانا والله أعلم بما تصفون ) أي : تذكرون . قال هذا في نفسه ، ولم يبده لهم ، وهذا من باب الإضمار قبل الذكر ، وهو كثير ، كقول الشاعر :\nجزى بنوه أبا الغيلان عن كبر وحسن فعل كما يجزى سنمار\nوله شواهد كثيرة في القرآن والحديث واللغة ، في منثورها وأخبارها وأشعارها .\nقال العوفي ، عن ابن عباس : ( فأسرها يوسف في نفسه ) قال : أسر في نفسه : ( أنتم شر مكانا والله أعلم بما تصفون )\n                                    ",
        "qortoby": "۞ قَالُوٓاْ إِن يَسۡرِقۡ فَقَدۡ سَرَقَ أَخٞ لَّهُۥ مِن قَبۡلُۚ فَأَسَرَّهَا يُوسُفُ فِي نَفۡسِهِۦ وَلَمۡ يُبۡدِهَا لَهُمۡۚ قَالَ أَنتُمۡ شَرّٞ مَّكَانٗاۖ وَٱللَّهُ أَعۡلَمُ بِمَا تَصِفُونَ ٧٧\n                                    \n                                    \n                                    قوله تعالى : قالوا إن يسرق فقد سرق أخ له من قبل المعنى : أي اقتدى بأخيه ، ولو اقتدى بنا ما سرق ; وإنما قالوا ذلك ليبرءوا من فعله ، لأنه ليس من أمهم ; وأنه إن سرق فقد جذبه عرق أخيه السارق ; لأن الاشتراك في الأنساب يشاكل في الأخلاق . وقد اختلفوا في السرقة التي نسبوا إلى يوسف ; فروي عن مجاهد وغيره أن عمة يوسف بنت إسحاق كانت أكبر من يعقوب ، وكانت صارت إليها منطقة إسحاق لسنها ; لأنهم كانوا يتوارثون بالسن ، وهذا مما نسخ حكمه بشرعنا ، وكان من سرق استعبد . وكانت عمة يوسف حضنته وأحبته حبا شديدا ; فلما ترعرع وشب قال لها يعقوب : سلمي يوسف إلي ، فلست أقدر أن يغيب عني ساعة ; فولعت به ، وأشفقت من فراقه ; فقالت له : دعه عندي أياما أنظر إليه فلما خرج من عندها يعقوب عمدت إلى منطقة إسحاق ، فحزمتها على يوسف من تحت ثيابه ، ثم قالت : لقد فقدت منطقة إسحاق ، فانظروا من أخذها ومن أصابها ; فالتمست ثم قالت : اكشفوا أهل البيت فكشفوا ; فوجدت مع يوسف . فقالت : إنه والله لي سلم أصنع فيه ما شئت ; ثم أتاها يعقوب فأخبرته الخبر ، فقال لها : أنت وذلك ، إن كان فعل ذلك فهو سلم لك ; فأمسكته حتى ماتت ; فبذلك عيره إخوته في قولهم : إن يسرق فقد سرق أخ له من قبل ومن هاهنا تعلم يوسف وضع السقاية في رحل أخيه كما عملت به عمته . وقال سعيد بن جبير : إنما أمرته أن يسرق صنما كان لجده أبي أمه ، فسرقه وكسره وألقاه على الطريق ، وكان ذلك منهما تغييرا للمنكر ; فرموه بالسرقة وعيروه بها ، وقال قتادة وفي كتاب الزجاج : أنه كان صنم ذهب . وقال عطية العوفي : إنه كان مع إخوته على طعام فنظر إلى عرق فخبأه فعيروه بذلك . وقيل : إنه كان يسرق من طعام المائدة للمساكين ; حكاه ابن عيسى وقيل : إنهم كذبوا عليه فيما نسبوه إليه ; قاله الحسن\nقوله تعالى : فأسرها يوسف في نفسه ولم يبدها لهم أي أسر في نفسه قولهم إن يسرق فقد سرق أخ له من قبل قاله ابن شجرة وابن عيسى . وقيل : إنه أسر في نفسه قوله : أنتم شر مكانا ثم جهر فقال : والله أعلم بما تصفون . قاله ابن عباس ،\nقال أنتم شر مكانا أي أنتم شر مكانا ممن نسبتموه إلى هذه السرقة .\nومعنى قوله : والله أعلم بما تصفون أي الله أعلم أن ما قلتم كذب ، وإن كانت لله رضا . وقد قيل : إن إخوة يوسف في ذلك الوقت ما كانوا أنبياء .\n                                    ",
        "saadi": "۞ قَالُوٓاْ إِن يَسۡرِقۡ فَقَدۡ سَرَقَ أَخٞ لَّهُۥ مِن قَبۡلُۚ فَأَسَرَّهَا يُوسُفُ فِي نَفۡسِهِۦ وَلَمۡ يُبۡدِهَا لَهُمۡۚ قَالَ أَنتُمۡ شَرّٞ مَّكَانٗاۖ وَٱللَّهُ أَعۡلَمُ بِمَا تَصِفُونَ ٧٧\n                                        \n                                        \n                                        \n                                        فلما رأى إخوة يوسف ما رأوا { قَالُوا إِنْ يَسْرِقْ } هذا الأخ، فليس هذا غريبا منه. { فَقَدْ سَرَقَ أَخٌ لَهُ مِنْ قَبْلُ } يعنون: يوسف عليه السلام، ومقصودهم تبرئة أنفسهم وأن هذا وأخاه قد يصدر منهما ما يصدر من السرقة، وهما ليسا شقيقين لنا.\nوفي هذا من الغض عليهما ما فيه، ولهذا: أسرها يوسف في نفسه { وَلَمْ يُبْدِهَا لَهُمْ } أي: لم يقابلهم على ما قالوه بما يكرهون، بل كظم الغيظ، وأسرَّ الأمر في نفسه. و { قَالَ } في نفسه { أَنْتُمْ شَرٌّ مَكَانًا } حيث ذممتمونا بما أنتم على أشر منه، { وَاللَّهُ أَعْلَمُ بِمَا تَصِفُونَ } منا، من وصفنا بالسرقة، يعلم الله أنا براء منها، ثم سلكوا معه مسلك التملق، لعله يسمح لهم بأخيهم.\n                                    "
      },
      "originalText": "۞ قَالُوٓاْ إِن يَسۡرِقۡ فَقَدۡ سَرَقَ أَخٞ لَّهُۥ مِن قَبۡلُۚ فَأَسَرَّهَا يُوسُفُ فِي نَفۡسِهِۦ وَلَمۡ يُبۡدِهَا لَهُمۡۚ قَالَ أَنتُمۡ شَرّٞ مَّكَانٗاۖ وَٱللَّهُ أَعۡلَمُ بِمَا تَصِفُونَ ٧٧"
    },
    {
      "number": 1674,
      "text": "قَالُوا يَا أَيُّهَا الْعَزِيزُ إِنَّ لَهُ أَبًا شَيْخًا كَبِيرًا فَخُذْ أَحَدَنَا مَكَانَهُ ۖ إِنَّا نَرَاكَ مِنَ الْمُحْسِنِينَ",
      "surah": {
        "number": 12,
        "name": "سورة يوسف",
        "englishName": "Yusuf",
        "englishNameTranslation": "Joseph",
        "revelationType": "Meccan",
        "numberOfAyahs": 111
      },
      "numberInSurah": 78,
      "juz": 13,
      "manzil": 3,
      "page": 244,
      "ruku": 201,
      "hizbQuarter": 98,
      "sajda": false,
      "tafsier": {
        "ibnkther": "قَالُواْ يَٰٓأَيُّهَا ٱلۡعَزِيزُ إِنَّ لَهُۥٓ أَبٗا شَيۡخٗا كَبِيرٗا فَخُذۡ أَحَدَنَا مَكَانَهُۥٓۖ إِنَّا نَرَىٰكَ مِنَ ٱلۡمُحۡسِنِينَ ٨٧\n                                    \n                                    \n                                    لما تعين أخذ بنيامين وتقرر تركه عند يوسف بمقتضى اعترافهم ، شرعوا يترققون له ويعطفونه عليهم ، ف ( قالوا يا أيها العزيز إن له أبا شيخا كبيرا ) يعنون : وهو يحبه حبا شديدا ويتسلى به عن ولده الذي فقده ، ( فخذ أحدنا مكانه ) أي : بدله ، يكون عندك عوضا عنه ، ( إنا نراك من المحسنين ) أي : من العادلين المنصفين القابلين للخير .\n                                    ",
        "qortoby": "قَالُواْ يَٰٓأَيُّهَا ٱلۡعَزِيزُ إِنَّ لَهُۥٓ أَبٗا شَيۡخٗا كَبِيرٗا فَخُذۡ أَحَدَنَا مَكَانَهُۥٓۖ إِنَّا نَرَىٰكَ مِنَ ٱلۡمُحۡسِنِينَ ٨٧\n                                    \n                                    \n                                    قوله تعالى : قالوا يا أيها العزيز إن له أبا شيخا كبيرا فخذ أحدنا مكانه خاطبوه باسم العزيز إذ كان في تلك اللحظة بعزل الأول أو موته . وقولهم : إن له أبا شيخا كبيرا أي كبير القدر ، ولم يريدوا كبر السن ; لأن ذلك معروف من حال الشيخ . فخذ أحدنا مكانه أي عبدا بدله ; وقد قيل : إن هذا مجاز ; لأنهم يعلمون أنه لا يصح أخذ حر يسترق بدل من قد أحكمت السنة عندهم رقه ; وإنما هذا كما تقول لمن تكره فعله : اقتلني ولا تفعل كذا وكذا ، وأنت لا تريد أن يقتلك ، ولكنك مبالغ في استنزاله . ويحتمل أن يكون قولهم : فخذ أحدنا مكانه حقيقة ; وبعيد عليهم وهم أنبياء أن يروا استرقاق حر ، فلم يبق إلا أن يريدوا بذلك طريق الحمالة ; أي خذ أحدنا مكانه . حتى ينصرف إليك صاحبك ; ومقصدهم بذلك أن يصل بنيامين إلى أبيه ; ويعرف يعقوب جلية الأمر ; فمنع يوسف - عليه السلام - من ذلك ، إذ الحمالة في الحدود ونحوها - بمعنى إحضار المضمون فقط - جائزة مع التراضي ، غير لازمة إذا أبى الطالب ; وأما الحمالة في مثل هذا على أن يلزم الحميل ما كان يلزم المضمون من عقوبة ، فلا يجوز إجماعا . وفي \" الواضحة \" : إن الحمالة في الوجه فقط في جميع الحدود جائزة ، إلا في النفس . وجمهور الفقهاء على جواز الكفالة في النفس . واختلف فيها عن الشافعي ; فمرة ضعفها ، ومرة أجازها .\nقوله تعالى : إنا نراك من المحسنين يحتمل أن يريدوا وصفه بما رأوا من إحسانه في جميع أفعاله معهم ، ويحتمل أن يريدوا : إنا نرى لك إحسانا علينا في هذه اليد إن أسديتها إلينا ; وهذا تأويل ابن إسحاق .\n                                    ",
        "saadi": "قَالُواْ يَٰٓأَيُّهَا ٱلۡعَزِيزُ إِنَّ لَهُۥٓ أَبٗا شَيۡخٗا كَبِيرٗا فَخُذۡ أَحَدَنَا مَكَانَهُۥٓۖ إِنَّا نَرَىٰكَ مِنَ ٱلۡمُحۡسِنِينَ ٨٧\n                                        \n                                        \n                                        \n                                        فـ { قَالُوا يَا أَيُّهَا الْعَزِيزُ إِنَّ لَهُ أَبًا شَيْخًا كَبِيرًا } أي: وإنه لا يصبر عنه، وسيشق عليه فراقه، { فَخُذْ أَحَدَنَا مَكَانَهُ إِنَّا نَرَاكَ مِنَ الْمُحْسِنِينَ } فأحسن إلينا وإلى أبينا بذلك.\n                                    "
      },
      "originalText": "قَالُواْ يَٰٓأَيُّهَا ٱلۡعَزِيزُ إِنَّ لَهُۥٓ أَبٗا شَيۡخٗا كَبِيرٗا فَخُذۡ أَحَدَنَا مَكَانَهُۥٓۖ إِنَّا نَرَىٰكَ مِنَ ٱلۡمُحۡسِنِينَ ٨٧"
    }
  ]
}